muzzy/__init__.py
muzzy/bytes.py
muzzy/core.py
muzzy/validators.py
muzzy-0.1.3.dist-info/LICENSE
muzzy-0.1.3.dist-info/METADATA
muzzy-0.1.3.dist-info/WHEEL
muzzy-0.1.3.dist-info/RECORD
