Metadata-Version: 2.3
Name: muzzy
Version: 0.1.3
Summary: A python function library
Author: wangshangwen
Author-email: shangwenwang20@gmail.com
Requires-Python: >=3.9
Classifier: Programming Language :: Python :: 3
Classifier: Programming Language :: Python :: 3.9
Classifier: Programming Language :: Python :: 3.10
Classifier: Programming Language :: Python :: 3.11
Classifier: Programming Language :: Python :: 3.12
Classifier: Programming Language :: Python :: 3.13
Requires-Dist: base32-tiny (>=0.1.3,<0.2.0)
Requires-Dist: setuptools (>=78.1.0,<79.0.0)
Requires-Dist: validators (>=0.34.0,<0.35.0)
